{
  "number": 1074,
  "url": "https://api.github.com/repos/emberjs/rfcs/pulls/1074",
  "title": "Deprecate `--yarn` support for `ember new`",
  "createdAt": "2025-01-30T22:20:38Z",
  "closedAt": null,
  "mergedAt": null,
  "assignees": [],
  "timelineItems": [
    {
      "event": "labeled",
      "createdAt": "2025-01-30T22:20:54Z",
      "label": "S-Proposed"
    },
    {
      "event": "unlabeled",
      "createdAt": "2025-02-07T19:57:34Z",
      "label": "S-Proposed"
    },
    {
      "event": "labeled",
      "createdAt": "2025-02-07T19:57:34Z",
      "label": "S-Exploring"
    }
  ],
  "currentStage": "exploring",
  "labels": [
    {
      "event": "labeled",
      "createdAt": "2025-02-07T19:57:34Z",
      "label": "S-Exploring"
    }
  ],
  "stageDuration": {
    "proposed": 8,
    "exploring": 174,
    "accepted": null,
    "release": null,
    "released": null
  },
  "connected": []
}