{
  "number": 639,
  "url": "https://api.github.com/repos/emberjs/rfcs/pulls/639",
  "title": "Replace terms blacklist & whitelist",
  "createdAt": "2020-06-15T11:17:47Z",
  "closedAt": "2020-07-24T19:51:12Z",
  "mergedAt": "2020-07-24T19:51:12Z",
  "assignees": [
    {
      "login": "MelSumner",
      "avatarUrl": "https://avatars.githubusercontent.com/u/4587451?v=4"
    }
  ],
  "timelineItems": [],
  "currentStage": "accepted",
  "labels": [],
  "fcp": false,
  "stageDuration": {
    "proposed": 1911,
    "exploring": null,
    "accepted": null,
    "release": null,
    "released": null
  },
  "connected": []
}