{
  "number": 682,
  "url": "https://api.github.com/repos/emberjs/rfcs/pulls/682",
  "title": "Update templates with new frontmatter style",
  "createdAt": "2020-11-09T22:01:04Z",
  "closedAt": "2020-11-12T16:14:51Z",
  "merged": true,
  "mergedAt": "2020-11-12T16:14:51Z",
  "assignees": [],
  "timelineItems": [],
  "currentStage": "accepted",
  "labels": [],
  "fcp": false,
  "stageDuration": {
    "proposed": 1764,
    "exploring": null,
    "accepted": null,
    "release": null,
    "released": null
  },
  "connected": []
}