{
  "number": 692,
  "url": "https://api.github.com/repos/emberjs/rfcs/pulls/692",
  "title": "Deprecate Array Observers",
  "createdAt": "2020-12-23T20:43:49Z",
  "closedAt": "2021-01-15T19:12:49Z",
  "merged": true,
  "mergedAt": "2021-01-15T19:12:49Z",
  "assignees": [],
  "timelineItems": [
    {
      "event": "labeled",
      "createdAt": "2021-01-08T19:28:29Z",
      "label": "Final Comment Period"
    }
  ],
  "currentStage": "accepted",
  "labels": [],
  "fcp": false,
  "stageDuration": {
    "proposed": 1720,
    "exploring": null,
    "accepted": null,
    "release": null,
    "released": null
  },
  "connected": []
}