{
  "number": 1112,
  "url": "https://api.github.com/repos/emberjs/rfcs/pulls/1112",
  "title": "Deprecate Ember Proxies",
  "createdAt": "2025-06-13T19:45:33Z",
  "closed": true,
  "closedAt": "2025-08-15T18:55:24Z",
  "merged": true,
  "mergedAt": "2025-08-15T18:55:24Z",
  "assignees": [],
  "timelineItems": [
    {
      "event": "labeled",
      "createdAt": "2025-06-13T19:45:46Z",
      "label": "S-Proposed"
    },
    {
      "event": "labeled",
      "createdAt": "2025-06-20T18:19:05Z",
      "label": "S-Exploring"
    },
    {
      "event": "unlabeled",
      "createdAt": "2025-06-20T18:19:16Z",
      "label": "S-Proposed"
    },
    {
      "event": "labeled",
      "createdAt": "2025-08-08T18:59:56Z",
      "label": "Final Comment Period"
    }
  ]
}